pytest_textual_snapshot.py
resources/snapshot_report_template.jinja2
pytest_textual_snapshot-1.1.0.dist-info/LICENSE
pytest_textual_snapshot-1.1.0.dist-info/METADATA
pytest_textual_snapshot-1.1.0.dist-info/WHEEL
pytest_textual_snapshot-1.1.0.dist-info/entry_points.txt
pytest_textual_snapshot-1.1.0.dist-info/RECORD
