Metadata-Version: 2.1
Name: pytest-textual-snapshot
Version: 1.1.0
Summary: Snapshot testing for Textual apps
Home-page: https://github.com/darrenburns/pytest-textual-snapshot
License: MIT
Author: Darren Burns
Author-email: darren@textualize.io
Maintainer: Will McGugan
Maintainer-email: will@textualize.io
Requires-Python: >=3.8.1,<4.0.0
Classifier: Development Status :: 5 - Production/Stable
Classifier: Framework :: Pytest
Classifier: Intended Audience :: Developers
Classifier: License :: OSI Approved :: MIT License
Classifier: Operating System :: OS Independent
Classifier: Programming Language :: Python
Classifier: Programming Language :: Python :: 3
Classifier: Programming Language :: Python :: 3.9
Classifier: Programming Language :: Python :: 3.10
Classifier: Programming Language :: Python :: 3.11
Classifier: Programming Language :: Python :: 3.12
Classifier: Programming Language :: Python :: 3 :: Only
Classifier: Programming Language :: Python :: 3.13
Classifier: Programming Language :: Python :: 3.8
Classifier: Programming Language :: Python :: Implementation :: CPython
Classifier: Programming Language :: Python :: Implementation :: PyPy
Classifier: Topic :: Software Development :: Testing
Requires-Dist: jinja2 (>=3.0.0)
Requires-Dist: pytest (>=8.0.0)
Requires-Dist: rich (>=12.0.0)
Requires-Dist: syrupy (==4.8.0)
Requires-Dist: textual (>=0.28.0)
